MANIFEST.in
README.md
bibbreviate
setup.py
bibbreviate.egg-info/PKG-INFO
bibbreviate.egg-info/SOURCES.txt
bibbreviate.egg-info/dependency_links.txt
bibbreviate.egg-info/entry_points.txt
bibbreviate.egg-info/requires.txt
bibbreviate.egg-info/top_level.txt
src/__init__.py
src/bibbrev.py
src/journal_files/journal_abbreviations_general.txt