Metadata-Version: 1.1
Name: bibbreviate
Version: 0.1
Summary: Abbreviate journal titles in BibTex files.
Home-page: https://github.com/Winawer/bibbreviate
Author: Steven Hamblin
Author-email: steven.hamblin@gmail.com
License: UNKNOWN
Platform: UNKNOWN
Classifier: Development Status :: 4 - Beta
Classifier: Environment :: Console
Classifier: Intended Audience :: Science/Research
Classifier: License :: OSI Approved :: MIT License
Classifier: Programming Language :: Python
Classifier: Topic :: Text Processing :: Markup :: LaTeX
